[
  {
    "ContainingType": "SIREC.Controllers.AuthController",
    "Method": "Login",
    "RelativePath": "api/Auth/login",
    "HttpMethod": "POST",
    "IsController": true,
    "Order": 0,
    "Parameters": [
      {
        "Name": "request",
        "Type": "SIREC.Models.LoginRequest",
        "IsRequired": true
      }
    ],
    "ReturnTypes": []
  },
  {
    "ContainingType": "SIREC.Controllers.AuthController",
    "Method": "Register",
    "RelativePath": "api/Auth/register",
    "HttpMethod": "POST",
    "IsController": true,
    "Order": 0,
    "Parameters": [
      {
        "Name": "usuario",
        "Type": "SIREC.Models.Usuario",
        "IsRequired": true
      },
      {
        "Name": "idRol",
        "Type": "System.Int32",
        "IsRequired": false
      }
    ],
    "ReturnTypes": []
  },
  {
    "ContainingType": "SIREC.Controllers.CitasController",
    "Method": "GetCitas",
    "RelativePath": "api/Citas",
    "HttpMethod": "GET",
    "IsController": true,
    "Order": 0,
    "Parameters": [],
    "ReturnTypes": [
      {
        "Type": "System.Collections.Generic.IEnumerable\u00601[[SIREC.Models.Cita, SIREC, Version=1.0.0.0, Culture=neutral, PublicKeyToken=null]]",
        "MediaTypes": [
          "text/plain",
          "application/json",
          "text/json"
        ],
        "StatusCode": 200
      }
    ]
  },
  {
    "ContainingType": "SIREC.Controllers.CitasController",
    "Method": "PostCita",
    "RelativePath": "api/Citas",
    "HttpMethod": "POST",
    "IsController": true,
    "Order": 0,
    "Parameters": [
      {
        "Name": "cita",
        "Type": "SIREC.Models.Cita",
        "IsRequired": true
      }
    ],
    "ReturnTypes": [
      {
        "Type": "SIREC.Models.Cita",
        "MediaTypes": [
          "text/plain",
          "application/json",
          "text/json"
        ],
        "StatusCode": 200
      }
    ]
  },
  {
    "ContainingType": "SIREC.Controllers.CitasController",
    "Method": "GetCita",
    "RelativePath": "api/Citas/{id}",
    "HttpMethod": "GET",
    "IsController": true,
    "Order": 0,
    "Parameters": [
      {
        "Name": "id",
        "Type": "System.Int32",
        "IsRequired": true
      }
    ],
    "ReturnTypes": [
      {
        "Type": "SIREC.Models.Cita",
        "MediaTypes": [
          "text/plain",
          "application/json",
          "text/json"
        ],
        "StatusCode": 200
      }
    ]
  },
  {
    "ContainingType": "SIREC.Controllers.CitasController",
    "Method": "PutCita",
    "RelativePath": "api/Citas/{id}",
    "HttpMethod": "PUT",
    "IsController": true,
    "Order": 0,
    "Parameters": [
      {
        "Name": "id",
        "Type": "System.Int32",
        "IsRequired": true
      },
      {
        "Name": "cita",
        "Type": "SIREC.Models.Cita",
        "IsRequired": true
      }
    ],
    "ReturnTypes": []
  },
  {
    "ContainingType": "SIREC.Controllers.CitasController",
    "Method": "DeleteCita",
    "RelativePath": "api/Citas/{id}",
    "HttpMethod": "DELETE",
    "IsController": true,
    "Order": 0,
    "Parameters": [
      {
        "Name": "id",
        "Type": "System.Int32",
        "IsRequired": true
      }
    ],
    "ReturnTypes": []
  },
  {
    "ContainingType": "SIREC.Controllers.CitasController",
    "Method": "ActualizarEstado",
    "RelativePath": "api/Citas/{id}/estado",
    "HttpMethod": "PUT",
    "IsController": true,
    "Order": 0,
    "Parameters": [
      {
        "Name": "id",
        "Type": "System.Int32",
        "IsRequired": true
      },
      {
        "Name": "body",
        "Type": "System.Text.Json.JsonElement",
        "IsRequired": true
      }
    ],
    "ReturnTypes": []
  },
  {
    "ContainingType": "SIREC.Controllers.CitasController",
    "Method": "ObtenerCitasPorMedico",
    "RelativePath": "api/Citas/medico/{idUsuario}",
    "HttpMethod": "GET",
    "IsController": true,
    "Order": 0,
    "Parameters": [
      {
        "Name": "idUsuario",
        "Type": "System.Int32",
        "IsRequired": true
      }
    ],
    "ReturnTypes": []
  },
  {
    "ContainingType": "SIREC.Controllers.CitasController",
    "Method": "ObtenerCitasUsuario",
    "RelativePath": "api/Citas/MisCitas",
    "HttpMethod": "GET",
    "IsController": true,
    "Order": 0,
    "Parameters": [],
    "ReturnTypes": [
      {
        "Type": "System.Collections.Generic.IEnumerable\u00601[[SIREC.Models.Cita, SIREC, Version=1.0.0.0, Culture=neutral, PublicKeyToken=null]]",
        "MediaTypes": [
          "text/plain",
          "application/json",
          "text/json"
        ],
        "StatusCode": 200
      }
    ]
  },
  {
    "ContainingType": "SIREC.Controllers.CitasController",
    "Method": "SolicitarCita",
    "RelativePath": "api/Citas/solicitar",
    "HttpMethod": "POST",
    "IsController": true,
    "Order": 0,
    "Parameters": [
      {
        "Name": "cita",
        "Type": "SIREC.Models.Cita",
        "IsRequired": true
      }
    ],
    "ReturnTypes": []
  },
  {
    "ContainingType": "SIREC.Controllers.CitasController",
    "Method": "GetCitasPorUsuario",
    "RelativePath": "api/Citas/usuario/{idUsuario}",
    "HttpMethod": "GET",
    "IsController": true,
    "Order": 0,
    "Parameters": [
      {
        "Name": "idUsuario",
        "Type": "System.Int32",
        "IsRequired": true
      }
    ],
    "ReturnTypes": [
      {
        "Type": "System.Collections.Generic.IEnumerable\u00601[[SIREC.Models.Cita, SIREC, Version=1.0.0.0, Culture=neutral, PublicKeyToken=null]]",
        "MediaTypes": [
          "text/plain",
          "application/json",
          "text/json"
        ],
        "StatusCode": 200
      }
    ]
  },
  {
    "ContainingType": "SIREC.Controllers.ConsultoriosController",
    "Method": "GetConsultorios",
    "RelativePath": "api/Consultorios",
    "HttpMethod": "GET",
    "IsController": true,
    "Order": 0,
    "Parameters": [],
    "ReturnTypes": [
      {
        "Type": "System.Collections.Generic.IEnumerable\u00601[[SIREC.Models.Consultorio, SIREC, Version=1.0.0.0, Culture=neutral, PublicKeyToken=null]]",
        "MediaTypes": [
          "text/plain",
          "application/json",
          "text/json"
        ],
        "StatusCode": 200
      }
    ]
  },
  {
    "ContainingType": "SIREC.Controllers.ConsultoriosController",
    "Method": "PostConsultorio",
    "RelativePath": "api/Consultorios",
    "HttpMethod": "POST",
    "IsController": true,
    "Order": 0,
    "Parameters": [
      {
        "Name": "consultorio",
        "Type": "SIREC.Models.Consultorio",
        "IsRequired": true
      }
    ],
    "ReturnTypes": [
      {
        "Type": "SIREC.Models.Consultorio",
        "MediaTypes": [
          "text/plain",
          "application/json",
          "text/json"
        ],
        "StatusCode": 200
      }
    ]
  },
  {
    "ContainingType": "SIREC.Controllers.ConsultoriosController",
    "Method": "GetConsultorio",
    "RelativePath": "api/Consultorios/{id}",
    "HttpMethod": "GET",
    "IsController": true,
    "Order": 0,
    "Parameters": [
      {
        "Name": "id",
        "Type": "System.Int32",
        "IsRequired": true
      }
    ],
    "ReturnTypes": [
      {
        "Type": "SIREC.Models.Consultorio",
        "MediaTypes": [
          "text/plain",
          "application/json",
          "text/json"
        ],
        "StatusCode": 200
      }
    ]
  },
  {
    "ContainingType": "SIREC.Controllers.ConsultoriosController",
    "Method": "PutConsultorio",
    "RelativePath": "api/Consultorios/{id}",
    "HttpMethod": "PUT",
    "IsController": true,
    "Order": 0,
    "Parameters": [
      {
        "Name": "id",
        "Type": "System.Int32",
        "IsRequired": true
      },
      {
        "Name": "consultorio",
        "Type": "SIREC.Models.Consultorio",
        "IsRequired": true
      }
    ],
    "ReturnTypes": []
  },
  {
    "ContainingType": "SIREC.Controllers.ConsultoriosController",
    "Method": "DeleteConsultorio",
    "RelativePath": "api/Consultorios/{id}",
    "HttpMethod": "DELETE",
    "IsController": true,
    "Order": 0,
    "Parameters": [
      {
        "Name": "id",
        "Type": "System.Int32",
        "IsRequired": true
      }
    ],
    "ReturnTypes": []
  },
  {
    "ContainingType": "SIREC.Controllers.MedicoConsultorioController",
    "Method": "AsignarMedico",
    "RelativePath": "api/MedicoConsultorio",
    "HttpMethod": "POST",
    "IsController": true,
    "Order": 0,
    "Parameters": [
      {
        "Name": "asignacion",
        "Type": "SIREC.Models.MedicoConsultorio",
        "IsRequired": true
      }
    ],
    "ReturnTypes": []
  },
  {
    "ContainingType": "SIREC.Controllers.MedicoConsultorioController",
    "Method": "ObtenerAsignaciones",
    "RelativePath": "api/MedicoConsultorio",
    "HttpMethod": "GET",
    "IsController": true,
    "Order": 0,
    "Parameters": [],
    "ReturnTypes": []
  },
  {
    "ContainingType": "SIREC.Controllers.MedicoConsultorioController",
    "Method": "EliminarAsignacion",
    "RelativePath": "api/MedicoConsultorio/{id}",
    "HttpMethod": "DELETE",
    "IsController": true,
    "Order": 0,
    "Parameters": [
      {
        "Name": "id",
        "Type": "System.Int32",
        "IsRequired": true
      }
    ],
    "ReturnTypes": []
  },
  {
    "ContainingType": "SIREC.Controllers.MedicoConsultorioController",
    "Method": "ObtenerConsultoriosPorMedico",
    "RelativePath": "api/MedicoConsultorio/usuario/{idUsuario}",
    "HttpMethod": "GET",
    "IsController": true,
    "Order": 0,
    "Parameters": [
      {
        "Name": "idUsuario",
        "Type": "System.Int32",
        "IsRequired": true
      }
    ],
    "ReturnTypes": []
  },
  {
    "ContainingType": "SIREC.Controllers.UsuarioController",
    "Method": "GetUsuarios",
    "RelativePath": "api/Usuario",
    "HttpMethod": "GET",
    "IsController": true,
    "Order": 0,
    "Parameters": [],
    "ReturnTypes": []
  },
  {
    "ContainingType": "SIREC.Controllers.UsuarioController",
    "Method": "PostUsuario",
    "RelativePath": "api/Usuario",
    "HttpMethod": "POST",
    "IsController": true,
    "Order": 0,
    "Parameters": [
      {
        "Name": "usuario",
        "Type": "SIREC.Models.Usuario",
        "IsRequired": true
      }
    ],
    "ReturnTypes": [
      {
        "Type": "SIREC.Models.Usuario",
        "MediaTypes": [
          "text/plain",
          "application/json",
          "text/json"
        ],
        "StatusCode": 200
      }
    ]
  },
  {
    "ContainingType": "SIREC.Controllers.UsuarioController",
    "Method": "GetUsuario",
    "RelativePath": "api/Usuario/{id}",
    "HttpMethod": "GET",
    "IsController": true,
    "Order": 0,
    "Parameters": [
      {
        "Name": "id",
        "Type": "System.Int32",
        "IsRequired": true
      }
    ],
    "ReturnTypes": []
  },
  {
    "ContainingType": "SIREC.Controllers.UsuarioController",
    "Method": "PutUsuario",
    "RelativePath": "api/Usuario/{id}",
    "HttpMethod": "PUT",
    "IsController": true,
    "Order": 0,
    "Parameters": [
      {
        "Name": "id",
        "Type": "System.Int32",
        "IsRequired": true
      },
      {
        "Name": "usuario",
        "Type": "SIREC.Models.Usuario",
        "IsRequired": true
      }
    ],
    "ReturnTypes": []
  },
  {
    "ContainingType": "SIREC.Controllers.UsuarioController",
    "Method": "DeleteUsuario",
    "RelativePath": "api/Usuario/{id}",
    "HttpMethod": "DELETE",
    "IsController": true,
    "Order": 0,
    "Parameters": [
      {
        "Name": "id",
        "Type": "System.Int32",
        "IsRequired": true
      }
    ],
    "ReturnTypes": []
  },
  {
    "ContainingType": "SIREC.Controllers.UsuarioController",
    "Method": "GetMedicos",
    "RelativePath": "api/Usuario/medicos",
    "HttpMethod": "GET",
    "IsController": true,
    "Order": 0,
    "Parameters": [],
    "ReturnTypes": []
  },
  {
    "ContainingType": "SIREC.Controllers.WeatherForecastController",
    "Method": "Get",
    "RelativePath": "WeatherForecast",
    "HttpMethod": "GET",
    "IsController": true,
    "Order": 0,
    "Parameters": [],
    "ReturnTypes": [
      {
        "Type": "System.Collections.Generic.IEnumerable\u00601[[SIREC.WeatherForecast, SIREC, Version=1.0.0.0, Culture=neutral, PublicKeyToken=null]]",
        "MediaTypes": [
          "text/plain",
          "application/json",
          "text/json"
        ],
        "StatusCode": 200
      }
    ],
    "EndpointName": "GetWeatherForecast"
  }
]